numpy_cloud/__init__.py
numpy_cloud/util.py
numpy_cloud/client/__init__.py
numpy_cloud/client/cloud_array.py
numpy_cloud/client/config.py
numpy_cloud/client/npc.py
numpy_cloud/server/__init__.py
numpy_cloud/server/server.py
tests/__init__.py
tests/test_cloud_array.py
numpy_cloud-0.0.5.dist-info/LICENSE
numpy_cloud-0.0.5.dist-info/LICENSE~
numpy_cloud-0.0.5.dist-info/METADATA
numpy_cloud-0.0.5.dist-info/WHEEL
numpy_cloud-0.0.5.dist-info/top_level.txt
numpy_cloud-0.0.5.dist-info/RECORD
