Metadata-Version: 2.1
Name: numpy-cloud
Version: 0.0.5
Summary: Numpy in the cloud
Home-page: https://github.com/ortutay/numpy_cloud
Author: Numpy In The Cloud
Author-email: author@example.com
License: UNKNOWN
Platform: UNKNOWN
Classifier: Programming Language :: Python :: 3
Classifier: Operating System :: OS Independent
